anyblok/__init__.py
anyblok/_graphviz.py
anyblok/blok.py
anyblok/column.py
anyblok/common.py
anyblok/config.py
anyblok/conftest.py
anyblok/core.py
anyblok/declarations.py
anyblok/environment.py
anyblok/event.py
anyblok/field.py
anyblok/imp.py
anyblok/logging.py
anyblok/mapper.py
anyblok/migration.py
anyblok/mixin.py
anyblok/pkg_metadata.py
anyblok/plugins.py
anyblok/registry.py
anyblok/relationship.py
anyblok/release.py
anyblok/schema.py
anyblok/scripts.py
anyblok/testing.py
anyblok/version.py
anyblok/authorization/__init__.py
anyblok/authorization/binding.py
anyblok/authorization/query.py
anyblok/authorization/rule/__init__.py
anyblok/authorization/rule/attraccess.py
anyblok/authorization/rule/base.py
anyblok/authorization/rule/modelaccess.py
anyblok/bloks/__init__.py
anyblok/bloks/anyblok-logo_alpha_256.png
anyblok/bloks/anyblok_core/CODE.rst
anyblok/bloks/anyblok_core/__init__.py
anyblok/bloks/anyblok_core/authorization.py
anyblok/bloks/anyblok_core/exceptions.py
anyblok/bloks/anyblok_core/core/__init__.py
anyblok/bloks/anyblok_core/core/base.py
anyblok/bloks/anyblok_core/core/instrumentedlist.py
anyblok/bloks/anyblok_core/core/query.py
anyblok/bloks/anyblok_core/core/session.py
anyblok/bloks/anyblok_core/core/sqlbase.py
anyblok/bloks/anyblok_core/core/sqlviewbase.py
anyblok/bloks/anyblok_core/documentation/__init__.py
anyblok/bloks/anyblok_core/documentation/blok.py
anyblok/bloks/anyblok_core/documentation/model/__init__.py
anyblok/bloks/anyblok_core/documentation/model/attribute.py
anyblok/bloks/anyblok_core/documentation/model/field.py
anyblok/bloks/anyblok_core/system/__init__.py
anyblok/bloks/anyblok_core/system/blok.py
anyblok/bloks/anyblok_core/system/cache.py
anyblok/bloks/anyblok_core/system/parameter.py
anyblok/bloks/anyblok_core/system/sequence.py
anyblok/bloks/anyblok_core/tests/__init__.py
anyblok/bloks/anyblok_core/tests/test_core_base.py
anyblok/bloks/anyblok_core/tests/test_core_query.py
anyblok/bloks/anyblok_core/tests/test_core_sql_base.py
AnyBlok-2.2.0.dist-info/LICENSE
AnyBlok-2.2.0.dist-info/METADATA
AnyBlok-2.2.0.dist-info/WHEEL
AnyBlok-2.2.0.dist-info/entry_points.txt
AnyBlok-2.2.0.dist-info/top_level.txt
AnyBlok-2.2.0.dist-info/RECORD
