Metadata-Version: 2.1
Name: AnyBlok
Version: 2.2.0
Summary: Anyblok is a dynamic injection blok framework
Author-email: Jean-Sébastien Suzanne <jssuzanne@anybox.fr>
License: MPL2
Project-URL: Homepage, https://doc.anyblok.org/en/1.4.0/
Keywords: django,notifications,delayed sending
Classifier: Development Status :: 5 - Production/Stable
Classifier: Intended Audience :: Developers
Classifier: Programming Language :: Python :: 3.7
Classifier: Programming Language :: Python :: 3.8
Classifier: Programming Language :: Python :: 3.9
Classifier: Programming Language :: Python :: 3.10
Classifier: Programming Language :: Python :: 3.11
Classifier: Programming Language :: Python :: 3.12
Classifier: Programming Language :: Python :: Implementation :: CPython
Classifier: Programming Language :: Python :: Implementation :: PyPy
Classifier: Topic :: Database
Classifier: Topic :: Software Development
Classifier: Topic :: Software Development :: Libraries :: Python Modules
Classifier: License :: OSI Approved :: Mozilla Public License 2.0 (MPL 2.0)
Requires-Python: >=3.7
License-File: LICENSE
Requires-Dist: sqlalchemy >=2.0
Requires-Dist: sqlalchemy-utils >=0.40
Requires-Dist: sqlalchemy-views >=0.3.2
Requires-Dist: packaging
Requires-Dist: argparse
Requires-Dist: alembic
Requires-Dist: graphviz
Requires-Dist: PyYAML
Requires-Dist: appdirs
Requires-Dist: pytz
Requires-Dist: python-dateutil
Requires-Dist: texttable
Requires-Dist: testfixtures
Requires-Dist: importlib-metadata
Provides-Extra: mariadb
Requires-Dist: mysqlclient ; extra == 'mariadb'
Provides-Extra: mssql
Requires-Dist: pymssql ; extra == 'mssql'
Requires-Dist: sqlalchemy-utils ==0.34.2 ; extra == 'mssql'
Provides-Extra: mysql
Requires-Dist: mysqlclient ; extra == 'mysql'
Provides-Extra: postgres
Requires-Dist: psycopg2-binary ; extra == 'postgres'
Provides-Extra: pyodbc
Requires-Dist: pyodbc ; extra == 'pyodbc'
Provides-Extra: pytest
Requires-Dist: pytest ; extra == 'pytest'
Requires-Dist: pytest-cov ; extra == 'pytest'
